{
  "$schema": "https://mintlify.com/schema.json",
  "name": "enjoyelec",
  "logo": {
    "dark": "/logo/enjoyelec.png",
    "light": "/logo/enjoyelec.png"
  },
  "favicon": "/logo/enjoyelec-e.png",
  "colors": {
    "primary": "#0D9373",
    "light": "#07C983",
    "dark": "#0D9373",
    "anchors": {
      "from": "#0D9373",
      "to": "#07C983"
    }
  },
  "topbarLinks": [
    {
      "name": "Home",
      "url": "https://www.enjoyelec.net/"
    }
  ],
  "topbarCtaButton": {
    "name": "Get Started",
    "url": "https://enjoyelec.mintlify.app/"
  },
  "tabs": [
    {
      "name": "API Reference",
      "url": "api-reference"
    }
  ],
  "anchors": [
    {
      "name": "Documentation",
      "icon": "book-open-cover",
      "url": "https://mintlify.com/docs"
    },
    {
      "name": "API Reference",
      "openapi": "/api-reference/openapi.json",
      "url": "api-reference",
      "icon": "square-terminal"
    }
  ],
  "navigation": [
    {
      "group": "Get Started",
      "pages": [
        "introduction",
        "quickstart",
        "development"
      ]
    },
    {
      "group": "Essentials",
      "pages": [
        "essentials/markdown",
        "essentials/code",
        "essentials/images",
        "essentials/settings",
        "essentials/navigation",
        "essentials/reusable-snippets"
      ]
    },
    {
      "group": "API Documentation",
      "pages": [
        "api-reference"
      ]
    },
    {
      "group": "Endpoint Examples",
      "pages": [
        "api-reference/endpoint/get",
        "api-reference/endpoint/create",
        "api-reference/endpoint/delete"
      ]
    }
  ],
  "footerSocials": {
    "enjoyelec":"https://www.enjoyelec.net/"
  }
}